delft3dfmpy/__init__.py
delft3dfmpy/converters/hydamo_to_dflowfm.py
delft3dfmpy/converters/hydamo_to_dflowrr.py
delft3dfmpy/converters/sobek3_to_dflowfm.py
delft3dfmpy/core/checks.py
delft3dfmpy/core/dfm.py
delft3dfmpy/core/drr.py
delft3dfmpy/core/geometry.py
delft3dfmpy/core/logging.py
delft3dfmpy/core/mesh2d.py
delft3dfmpy/datamodels/common.py
delft3dfmpy/datamodels/cstructures.py
delft3dfmpy/datamodels/hydamo.py
delft3dfmpy/datamodels/osm.py
delft3dfmpy/datamodels/threedi2fm.py
delft3dfmpy/io/UgridReader.py
delft3dfmpy/io/UgridWriter.py
delft3dfmpy/io/dflowfmwriter.py
delft3dfmpy/io/dflowrrwriter.py
delft3dfmpy/io/dfmreader.py
delft3dfmpy/io/drrreader.py
delft3dfmpy/io/gridio.py
delft3dfmpy/io/resources/FMmdu.txt
delft3dfmpy/io/resources/RRmodel/3BRUNOFF.TP
delft3dfmpy/io/resources/RRmodel/3b_rout.3b
delft3dfmpy/io/resources/RRmodel/BERGCOEF
delft3dfmpy/io/resources/RRmodel/Bergcoef.cap
delft3dfmpy/io/resources/RRmodel/Bound3B.tbl
delft3dfmpy/io/resources/RRmodel/CROPFACT
delft3dfmpy/io/resources/RRmodel/CROP_OW.PRN
delft3dfmpy/io/resources/RRmodel/CropData.Dat
delft3dfmpy/io/resources/RRmodel/CropOwData.Dat
delft3dfmpy/io/resources/RRmodel/DELFT_3B.INI
delft3dfmpy/io/resources/RRmodel/EVAPOR.GEM
delft3dfmpy/io/resources/RRmodel/EVAPOR.PLV
delft3dfmpy/io/resources/RRmodel/KASGEBR
delft3dfmpy/io/resources/RRmodel/KASINIT
delft3dfmpy/io/resources/RRmodel/KASKLASS
delft3dfmpy/io/resources/RRmodel/KasGebrData.Dat
delft3dfmpy/io/resources/RRmodel/KasInitData.Dat
delft3dfmpy/io/resources/RRmodel/KasKlasData.Dat
delft3dfmpy/io/resources/RRmodel/Paved.tbl
delft3dfmpy/io/resources/RRmodel/ROOT_SIM.INP
delft3dfmpy/io/resources/RRmodel/SOBEK_3B.LNG
delft3dfmpy/io/resources/RRmodel/Sobek_3b.fnm
delft3dfmpy/io/resources/RRmodel/SoilData.Dat
delft3dfmpy/io/resources/RRmodel/UNSA_SIM.INP
delft3dfmpy/io/resources/RRmodel/Unpaved.tbl
delft3dfmpy/io/resources/RRmodel/pluvius.dwa
delft3dfmpy/lib/gridgeom.dll
delft3dfmpy-2.0.3.dist-info/LICENSE
delft3dfmpy-2.0.3.dist-info/WHEEL
delft3dfmpy-2.0.3.dist-info/METADATA
delft3dfmpy-2.0.3.dist-info/RECORD
