Metadata-Version: 2.1
Name: delft3dfmpy
Version: 2.0.3
Summary: Top-level package for delft3dfmpy.
Home-page: https://github.com/openearth/delft3dfmpy
Keywords: hydraulics hydrology data-science delft3dfm deltares hkv hydamo
Author: Deltares - HKV
Author-email: hurkmans@hkv.nl
Requires-Python: >=3.6
Classifier: License :: OSI Approved :: MIT License
Requires-Dist: geopandas
Requires-Dist: rasterio
Requires-Dist: imod
Requires-Dist: numpy
Requires-Dist: scipy
Requires-Dist: pandas
Requires-Dist: matplotlib
Requires-Dist: pillow
Requires-Dist: rasterstats
Requires-Dist: tqdm
Requires-Dist: netcdf4
Requires-Dist: descartes
Requires-Dist: contextily
Requires-Dist: hkvsobekpy
Requires-Dist: pytest ; extra == "dev"
Requires-Dist: pytest-cov ; extra == "dev"
Requires-Dist: black ; extra == "dev"
Requires-Dist: twine ; extra == "dev"
Requires-Dist: bumpversion ; extra == "dev"
Requires-Dist: watchdog ; extra == "dev"
Requires-Dist: coverage ; extra == "dev"
Requires-Dist: Sphinx ; extra == "dev"
Provides-Extra: dev
